{
  "id": "5f3adf755e8d",
  "owner": "thuanpham582002",
  "repoName": "tabby-mcp-server",
  "fullDescription": "Empower your terminal with AI-driven control and automation using the Tabby MCP server.",
  "techStack": [],
  "serviceTypes": [
    {
      "type": "automation",
      "label": "Automation",
      "icon": "⚡",
      "description": "Automates tasks and workflows"
    },
    {
      "type": "ai",
      "label": "Ai",
      "icon": "🤖",
      "description": "Leverages AI and machine learning"
    }
  ],
  "quality": {
    "score": 70,
    "factors": {
      "documentation": 60,
      "maintenance": 50,
      "community": 40,
      "performance": 85
    }
  },
  "metadata": {
    "complexity": "simple",
    "maturity": "stable",
    "deployment": [
      "local"
    ],
    "featured": false,
    "verified": false
  },
  "categorization": {
    "confidence": 1.95,
    "reason": "Keyword match analysis",
    "matched_keywords": [
      "terminal"
    ]
  },
  "usage": {
    "downloads": 0,
    "dependents": 0,
    "weeklyDownloads": 0
  },
  "installation": {
    "npm": null,
    "pip": null,
    "docker": null,
    "manual": null,
    "uv": null,
    "instructions": []
  },
  "repository": {
    "url": "https://github.com/thuanpham582002/tabby-mcp-server",
    "owner": "thuanpham582002",
    "name": "tabby-mcp-server",
    "stars": 0,
    "forks": 0,
    "lastUpdated": "2025-06-23T23:16:56.282Z",
    "watchers": 0,
    "openIssues": 0
  },
  "compatibility": {
    "platforms": [
      "web",
      "desktop"
    ],
    "requirements": []
  },
  "documentation": {
    "hasReadme": false,
    "hasExamples": false,
    "hasApiReference": false,
    "hasInstallation": false,
    "api": null
  },
  "allTags": [
    "tabby",
    "mcp",
    "utilities-tools",
    "server"
  ],
  "badges": [
    {
      "type": "complexity",
      "label": "Simple",
      "color": "#22c55e",
      "icon": "🟢"
    },
    {
      "type": "maturity",
      "label": "Stable",
      "color": "#10b981",
      "icon": "✅"
    }
  ],
  "icon": "⚡",
  "readme": null
}